jupyter_aas_timeseries/__init__.py
jupyter_aas_timeseries/_version.py
jupyter_aas_timeseries/figure.py
jupyter_aas_timeseries/static/extension.js
jupyter_aas_timeseries/static/index.js
jupyter_aas_timeseries/static/index.js.map
jupyter_aas_timeseries-0.1.7.data/data/etc/jupyter/nbconfig/notebook.d/jupyter-aas-timeseries.json
jupyter_aas_timeseries-0.1.7.data/data/share/jupyter/nbextensions/jupyter-aas-timeseries/extension.js
jupyter_aas_timeseries-0.1.7.data/data/share/jupyter/nbextensions/jupyter-aas-timeseries/index.js
jupyter_aas_timeseries-0.1.7.data/data/share/jupyter/nbextensions/jupyter-aas-timeseries/index.js.map
jupyter_aas_timeseries-0.1.7.dist-info/METADATA
jupyter_aas_timeseries-0.1.7.dist-info/WHEEL
jupyter_aas_timeseries-0.1.7.dist-info/top_level.txt
jupyter_aas_timeseries-0.1.7.dist-info/RECORD
