Metadata-Version: 2.1
Name: jupyter-aas-timeseries
Version: 0.1.7
Summary: Jupyter Widget for the AAS Time Series project
Home-page: https://github.com/aperiosoftware/jupyter-aas-timeseries
Author: Thomas Robitaille and Stuart Lowe
Author-email: thomas.robitaille@gmail.com
License: UNKNOWN
Keywords: ipython,jupyter,widgets
Platform: UNKNOWN
Classifier: Development Status :: 4 - Beta
Classifier: Framework :: IPython
Classifier: Intended Audience :: Developers
Classifier: Intended Audience :: Science/Research
Classifier: Topic :: Multimedia :: Graphics
Classifier: Programming Language :: Python :: 2
Classifier: Programming Language :: Python :: 2.7
Classifier: Programming Language :: Python :: 3
Classifier: Programming Language :: Python :: 3.3
Classifier: Programming Language :: Python :: 3.4
Classifier: Programming Language :: Python :: 3.5
Requires-Dist: ipywidgets (>=7.0.0)
